[
  {
    "iteration": 15,
    "reason": "periodic_goal_connected",
    "cost": 0.39560733210803684,
    "elapsed": 0.023175900045316666,
    "waypoints": 6,
    "path": [
      [
        1.44961732,
        -1.0,
        -2.13163078,
        1.02737597,
        0.79316053,
        0.23909477,
        -0.92881154,
        -0.72629612
      ],
      [
        1.45108452,
        -1.0,
        -2.1322849,
        1.01341601,
        0.76105626,
        0.08702465,
        -0.55285504,
        -0.43183084
      ],
      [
        1.45255172,
        -1.0,
        -2.13293902,
        0.99945605,
        0.728952,
        -0.06504547,
        -0.17689854,
        -0.13736557
      ],
      [
        1.45401892,
        -1.0,
        -2.13359314,
        0.9854961,
        0.69684773,
        -0.21711559,
        0.19905795,
        0.15709971
      ],
      [
        1.45548612,
        -1.0,
        -2.13424726,
        0.97153614,
        0.66474347,
        -0.36918571,
        0.57501445,
        0.45156499
      ],
      [
        1.45687276,
        -1.0,
        -2.13486546,
        0.95834271,
        0.634402,
        -0.51290591,
        0.9303278,
        0.72986166
      ]
    ]
  }
]
